{
  "_class": "shapePath",
  "booleanOperation": 3,
  "clippingMaskMode": 0,
  "do_objectID": "BF11C8BF-7CB1-4D55-ACB9-8F9CC6B6B3AB",
  "edited": true,
  "exportOptions": {
    "_class": "exportOptions",
    "do_objectID": "0578F490-4C08-4DE8-9AB0-E182B31AD0BE",
    "exportFormats": [
    ],
    "includedLayerIds": [
    ],
    "layerOptions": 0,
    "shouldTrim": false
  },
  "frame": {
    "_class": "rect",
    "constrainProportions": false,
    "do_objectID": "EFEB19DE-BC3F-4C1A-9EDA-013041A8A38A",
    "height": 14.16791181957658,
    "width": 14.16791181957659,
    "x": 4.721069301908373,
    "y": 4.722176105167598
  },
  "hasClippingMask": false,
  "isClosed": false,
  "isFixedToViewport": false,
  "isFlippedHorizontal": false,
  "isFlippedVertical": false,
  "isLocked": false,
  "isVisible": true,
  "layerListExpandedType": 0,
  "name": "Path",
  "nameIsFixed": false,
  "pointRadiusBehaviour": 1,
  "points": [
    {
      "_class": "curvePoint",
      "cornerRadius": 0,
      "curveFrom": "{0.22389313126184021, 1}",
      "curveMode": 4,
      "curveTo": "{0.49999023494717132, 1}",
      "hasCurveFrom": true,
      "hasCurveTo": false,
      "point": "{0.49999023494717132, 1}"
    },
    {
      "_class": "curvePoint",
      "cornerRadius": 0,
      "curveFrom": "{0, 0.22391266136749804}",
      "curveMode": 2,
      "curveTo": "{0, 0.7760873386325019}",
      "hasCurveFrom": true,
      "hasCurveTo": true,
      "point": "{0, 0.49999023494717104}"
    },
    {
      "_class": "curvePoint",
      "cornerRadius": 0,
      "curveFrom": "{0.77616545905513423, 0}",
      "curveMode": 2,
      "curveTo": "{0.22389313126184021, 0}",
      "hasCurveFrom": true,
      "hasCurveTo": true,
      "point": "{0.49999023494717132, 0}"
    },
    {
      "_class": "curvePoint",
      "cornerRadius": 0,
      "curveFrom": "{1, 0.7760873386325019}",
      "curveMode": 2,
      "curveTo": "{1, 0.22391266136749804}",
      "hasCurveFrom": true,
      "hasCurveTo": true,
      "point": "{1, 0.49999023494717104}"
    },
    {
      "_class": "curvePoint",
      "cornerRadius": 0,
      "curveFrom": "{0.49999023494717132, 1}",
      "curveMode": 4,
      "curveTo": "{0.77608733863250234, 1}",
      "hasCurveFrom": false,
      "hasCurveTo": true,
      "point": "{0.49999023494717132, 1}"
    }
  ],
  "resizingConstraint": 63,
  "resizingType": 0,
  "rotation": 0,
  "shouldBreakMaskChain": false,
  "style": {
    "_class": "style",
    "do_objectID": "260DC2CB-4528-4872-AAE9-611686F574F4",
    "endMarkerType": 0,
    "fills": [
      {
        "_class": "fill",
        "color": {
          "_class": "color",
          "alpha": 1,
          "blue": 0,
          "green": 0,
          "red": 0
        },
        "fillType": 0,
        "isEnabled": true,
        "noiseIndex": 0,
        "noiseIntensity": 0,
        "patternFillType": 1,
        "patternTileScale": 1
      }
    ],
    "miterLimit": 10,
    "startMarkerType": 0,
    "windingRule": 1
  }
}