{
  "_class": "shapePath",
  "booleanOperation": -1,
  "clippingMaskMode": 0,
  "do_objectID": "1BA8EB68-63D4-4252-A341-849B3A91FBBB",
  "edited": true,
  "exportOptions": {
    "_class": "exportOptions",
    "do_objectID": "CED20D61-2CFC-4169-BBBB-32BF1D413197",
    "exportFormats": [
    ],
    "includedLayerIds": [
    ],
    "layerOptions": 0,
    "shouldTrim": false
  },
  "frame": {
    "_class": "rect",
    "constrainProportions": false,
    "do_objectID": "E4A7EE8C-A733-4570-A24E-E1127F0A6D70",
    "height": 46.2,
    "width": 126.9333333333333,
    "x": 4.533333333333333,
    "y": 37.8
  },
  "hasClippingMask": false,
  "isClosed": true,
  "isFixedToViewport": false,
  "isFlippedHorizontal": false,
  "isFlippedVertical": false,
  "isLocked": false,
  "isVisible": true,
  "layerListExpandedType": 0,
  "name": "Path",
  "nameIsFixed": false,
  "pointRadiusBehaviour": 1,
  "points": [
    {
      "_class": "curvePoint",
      "cornerRadius": 0,
      "curveFrom": "{0.9464285714285714, 1}",
      "curveMode": 4,
      "curveTo": "{0.97601318303571438, 1}",
      "hasCurveFrom": false,
      "hasCurveTo": true,
      "point": "{0.9464285714285714, 1}"
    },
    {
      "_class": "curvePoint",
      "cornerRadius": 0,
      "curveFrom": "{0.023986816964285711, 1}",
      "curveMode": 4,
      "curveTo": "{0.053571428571428568, 1}",
      "hasCurveFrom": true,
      "hasCurveTo": false,
      "point": "{0.053571428571428568, 1}"
    },
    {
      "_class": "curvePoint",
      "cornerRadius": 0,
      "curveFrom": "{0, 0.86363636363636365}",
      "curveMode": 4,
      "curveTo": "{0, 0.93894264772727287}",
      "hasCurveFrom": false,
      "hasCurveTo": true,
      "point": "{0, 0.86363636363636365}"
    },
    {
      "_class": "curvePoint",
      "cornerRadius": 0,
      "curveFrom": "{0, 0}",
      "curveMode": 1,
      "curveTo": "{0, 0}",
      "hasCurveFrom": false,
      "hasCurveTo": false,
      "point": "{0, 0}"
    },
    {
      "_class": "curvePoint",
      "cornerRadius": 0,
      "curveFrom": "{1, 0}",
      "curveMode": 1,
      "curveTo": "{1, 0}",
      "hasCurveFrom": false,
      "hasCurveTo": false,
      "point": "{1, 0}"
    },
    {
      "_class": "curvePoint",
      "cornerRadius": 0,
      "curveFrom": "{1, 0.93894264772727287}",
      "curveMode": 4,
      "curveTo": "{1, 0.86363636363636365}",
      "hasCurveFrom": true,
      "hasCurveTo": false,
      "point": "{1, 0.86363636363636365}"
    }
  ],
  "resizingConstraint": 63,
  "resizingType": 0,
  "rotation": 0,
  "shouldBreakMaskChain": false,
  "style": {
    "_class": "style",
    "do_objectID": "2E9CD9DE-1783-4034-9D0D-D6DFAA0FDB03",
    "endMarkerType": 0,
    "miterLimit": 10,
    "startMarkerType": 0,
    "windingRule": 1
  }
}