{
  "_class": "symbolInstance",
  "booleanOperation": -1,
  "clippingMaskMode": 0,
  "do_objectID": "132D232D-B1C7-4DA4-812E-DF91EB21BFFB",
  "exportOptions": {
    "_class": "exportOptions",
    "do_objectID": "163F4010-C7E6-4D4B-A23D-1D3D010B73B3",
    "exportFormats": [
    ],
    "includedLayerIds": [
    ],
    "layerOptions": 0,
    "shouldTrim": false
  },
  "frame": {
    "_class": "rect",
    "constrainProportions": true,
    "do_objectID": "A7C8945F-2000-49AE-9D4C-F4836B10D6D7",
    "height": 24,
    "width": 24,
    "x": 236,
    "y": 13
  },
  "hasClippingMask": false,
  "horizontalSpacing": 0,
  "isFixedToViewport": false,
  "isFlippedHorizontal": false,
  "isFlippedVertical": false,
  "isLocked": false,
  "isVisible": true,
  "layerListExpandedType": 0,
  "name": "Icon",
  "nameIsFixed": true,
  "overrideValues": [
    {
      "_class": "overrideValue",
      "do_objectID": "88D6FC83-DDF9-4DA3-A72F-8212B2CF172F",
      "overrideName": "80D9EC47-76C6-4CBF-A415-56135FCE0F54_layerStyle",
      "value": "8275290C-BC62-48F5-85A6-CD6D9D6C64BA"
    }
  ],
  "resizingConstraint": 63,
  "resizingType": 0,
  "rotation": 0,
  "scale": 1,
  "shouldBreakMaskChain": false,
  "style": {
    "_class": "style",
    "do_objectID": "33CF7551-A275-47F8-972C-E4021AD7D8E6",
    "endMarkerType": 0,
    "miterLimit": 10,
    "startMarkerType": 0,
    "windingRule": 1
  },
  "symbolID": "11B7F22F-52A6-4E52-95BD-E03F40D350EA",
  "verticalSpacing": 0
}