{
  "_class": "shapePath",
  "booleanOperation": -1,
  "clippingMaskMode": 0,
  "do_objectID": "4BAA13BB-EA01-4BCD-83A6-08070179E944",
  "edited": true,
  "exportOptions": {
    "_class": "exportOptions",
    "do_objectID": "F8F85373-66F7-445F-A254-AC6592F2659D",
    "exportFormats": [
    ],
    "includedLayerIds": [
    ],
    "layerOptions": 0,
    "shouldTrim": false
  },
  "frame": {
    "_class": "rect",
    "constrainProportions": false,
    "do_objectID": "7216704B-AB6F-4A71-98BE-4AD61FC484B8",
    "height": 21.6676470588235,
    "width": 15.94226327944573,
    "x": 112.4133949191686,
    "y": 34.34117647058824
  },
  "hasClippingMask": false,
  "isClosed": false,
  "isFixedToViewport": false,
  "isFlippedHorizontal": false,
  "isFlippedVertical": false,
  "isLocked": false,
  "isVisible": true,
  "layerListExpandedType": 0,
  "name": "Fill 917",
  "nameIsFixed": false,
  "pointRadiusBehaviour": 1,
  "points": [
    {
      "_class": "curvePoint",
      "cornerRadius": 0,
      "curveFrom": "{0.55413360634758102, 1}",
      "curveMode": 1,
      "curveTo": "{0.55413360634758102, 1}",
      "hasCurveFrom": false,
      "hasCurveTo": false,
      "point": "{0.55413360634758102, 1}"
    },
    {
      "_class": "curvePoint",
      "cornerRadius": 0,
      "curveFrom": "{0.77169183516764794, 0.49607805624641282}",
      "curveMode": 4,
      "curveTo": "{1, 0.66673043810981425}",
      "hasCurveFrom": true,
      "hasCurveTo": false,
      "point": "{1, 0.66673043810981425}"
    },
    {
      "_class": "curvePoint",
      "cornerRadius": 0,
      "curveFrom": "{0.63066291272075725, 0}",
      "curveMode": 4,
      "curveTo": "{0.63066291272075725, 0.2604744595370192}",
      "hasCurveFrom": false,
      "hasCurveTo": true,
      "point": "{0.63066291272075725, 0}"
    },
    {
      "_class": "curvePoint",
      "cornerRadius": 0,
      "curveFrom": "{0, 0.39047254639372492}",
      "curveMode": 4,
      "curveTo": "{0, 0}",
      "hasCurveFrom": true,
      "hasCurveTo": false,
      "point": "{0, 0}"
    },
    {
      "_class": "curvePoint",
      "cornerRadius": 0,
      "curveFrom": "{0.55413360634758102, 1}",
      "curveMode": 4,
      "curveTo": "{0.21167135909905252, 0.7440214272048975}",
      "hasCurveFrom": false,
      "hasCurveTo": true,
      "point": "{0.55413360634758102, 1}"
    }
  ],
  "resizingConstraint": 63,
  "resizingType": 0,
  "rotation": 0,
  "shouldBreakMaskChain": false,
  "style": {
    "_class": "style",
    "do_objectID": "63210FA4-3600-4222-B162-A69C9A6CC02B",
    "endMarkerType": 0,
    "fills": [
      {
        "_class": "fill",
        "color": {
          "_class": "color",
          "alpha": 1,
          "blue": 1,
          "green": 1,
          "red": 1
        },
        "fillType": 0,
        "isEnabled": true,
        "noiseIndex": 0,
        "noiseIntensity": 0,
        "patternFillType": 1,
        "patternTileScale": 1
      }
    ],
    "miterLimit": 10,
    "startMarkerType": 0,
    "windingRule": 1
  }
}