{
  "_class": "shapePath",
  "booleanOperation": -1,
  "clippingMaskMode": 0,
  "do_objectID": "86B783B5-CA0A-4679-B149-6079FB8BC76D",
  "edited": true,
  "exportOptions": {
    "_class": "exportOptions",
    "do_objectID": "2750D365-F1B7-4F6E-82FC-2015FE5B7A81",
    "exportFormats": [
    ],
    "includedLayerIds": [
    ],
    "layerOptions": 0,
    "shouldTrim": false
  },
  "frame": {
    "_class": "rect",
    "constrainProportions": false,
    "do_objectID": "15F50938-D9E8-40F6-B2D4-0EBD64E21202",
    "height": 2.044117647058833,
    "width": 2.043879907621253,
    "x": 63.76905311778292,
    "y": 42.92647058823529
  },
  "hasClippingMask": false,
  "isClosed": true,
  "isFixedToViewport": false,
  "isFlippedHorizontal": false,
  "isFlippedVertical": false,
  "isLocked": false,
  "isVisible": true,
  "layerListExpandedType": 0,
  "name": "Fill 453",
  "nameIsFixed": false,
  "pointRadiusBehaviour": 1,
  "points": [
    {
      "_class": "curvePoint",
      "cornerRadius": 0,
      "curveFrom": "{0.3125, 0.82900000000000063}",
      "curveMode": 1,
      "curveTo": "{0.3125, 0.82900000000000063}",
      "hasCurveFrom": false,
      "hasCurveTo": false,
      "point": "{0.3125, 0.82900000000000063}"
    },
    {
      "_class": "curvePoint",
      "cornerRadius": 0,
      "curveFrom": "{0.6875, 0.82900000000000063}",
      "curveMode": 1,
      "curveTo": "{0.6875, 0.82900000000000063}",
      "hasCurveFrom": false,
      "hasCurveTo": false,
      "point": "{0.6875, 0.82900000000000063}"
    },
    {
      "_class": "curvePoint",
      "cornerRadius": 0,
      "curveFrom": "{0.6875, 0.17099999999999937}",
      "curveMode": 1,
      "curveTo": "{0.6875, 0.17099999999999937}",
      "hasCurveFrom": false,
      "hasCurveTo": false,
      "point": "{0.6875, 0.17099999999999937}"
    },
    {
      "_class": "curvePoint",
      "cornerRadius": 0,
      "curveFrom": "{0.3125, 0.17099999999999937}",
      "curveMode": 1,
      "curveTo": "{0.3125, 0.17099999999999937}",
      "hasCurveFrom": false,
      "hasCurveTo": false,
      "point": "{0.3125, 0.17099999999999937}"
    }
  ],
  "resizingConstraint": 63,
  "resizingType": 0,
  "rotation": 0,
  "shouldBreakMaskChain": false,
  "style": {
    "_class": "style",
    "do_objectID": "6B4F424D-B0C2-4224-A0A9-19D0495C0488",
    "endMarkerType": 0,
    "fills": [
      {
        "_class": "fill",
        "color": {
          "_class": "color",
          "alpha": 1,
          "blue": 0.051,
          "green": 0.07100000000000001,
          "red": 0.118
        },
        "fillType": 0,
        "isEnabled": true,
        "noiseIndex": 0,
        "noiseIntensity": 0,
        "patternFillType": 1,
        "patternTileScale": 1
      }
    ],
    "miterLimit": 10,
    "startMarkerType": 0,
    "windingRule": 1
  }
}