{
  "_class": "shapePath",
  "booleanOperation": -1,
  "clippingMaskMode": 0,
  "do_objectID": "A4486C83-3C0F-4A7E-A543-675D707F8A1B",
  "edited": true,
  "exportOptions": {
    "_class": "exportOptions",
    "do_objectID": "2144AC3E-B4BD-4C60-A9E2-BC5C18F600CD",
    "exportFormats": [
    ],
    "includedLayerIds": [
    ],
    "layerOptions": 0,
    "shouldTrim": false
  },
  "frame": {
    "_class": "rect",
    "constrainProportions": false,
    "do_objectID": "FD1B5882-E1A5-43BD-9DF4-9B822DD3308A",
    "height": 44.26834896254923,
    "width": 39.30296877352311,
    "x": 3.510537076570107,
    "y": 85.04281086613821
  },
  "hasClippingMask": false,
  "isClosed": true,
  "isFixedToViewport": false,
  "isFlippedHorizontal": false,
  "isFlippedVertical": false,
  "isLocked": false,
  "isVisible": true,
  "layerListExpandedType": 0,
  "name": "Path",
  "nameIsFixed": false,
  "pointRadiusBehaviour": 1,
  "points": [
    {
      "_class": "curvePoint",
      "cornerRadius": 0,
      "curveFrom": "{0.67946406476473298, 1}",
      "curveMode": 1,
      "curveTo": "{0.67946406476473298, 1}",
      "hasCurveFrom": false,
      "hasCurveTo": false,
      "point": "{0.67946406476473298, 1}"
    },
    {
      "_class": "curvePoint",
      "cornerRadius": 0,
      "curveFrom": "{0, 0.21057312046201174}",
      "curveMode": 1,
      "curveTo": "{0, 0.21057312046201174}",
      "hasCurveFrom": false,
      "hasCurveTo": false,
      "point": "{0, 0.21057312046201174}"
    },
    {
      "_class": "curvePoint",
      "cornerRadius": 0,
      "curveFrom": "{0.34908850944485686, 0}",
      "curveMode": 1,
      "curveTo": "{0.34908850944485686, 0}",
      "hasCurveFrom": false,
      "hasCurveTo": false,
      "point": "{0.34908850944485686, 0}"
    },
    {
      "_class": "curvePoint",
      "cornerRadius": 0,
      "curveFrom": "{1, 0.75625640811031358}",
      "curveMode": 1,
      "curveTo": "{1, 0.75625640811031358}",
      "hasCurveFrom": false,
      "hasCurveTo": false,
      "point": "{1, 0.75625640811031358}"
    }
  ],
  "resizingConstraint": 63,
  "resizingType": 0,
  "rotation": 0,
  "shouldBreakMaskChain": false,
  "style": {
    "_class": "style",
    "do_objectID": "AA75EAA9-9523-4ACF-8B52-A3192581DA4B",
    "endMarkerType": 0,
    "miterLimit": 10,
    "startMarkerType": 0,
    "windingRule": 1
  }
}