{
  "_class": "symbolMaster",
  "backgroundColor": {
    "_class": "color",
    "alpha": 1,
    "blue": 1,
    "do_objectID": "27CBDF33-2012-491A-8464-8C038A9BE2A6",
    "green": 1,
    "red": 1
  },
  "booleanOperation": -1,
  "changeIdentifier": 1657,
  "clippingMaskMode": 0,
  "do_objectID": "2D074AE3-601D-4EDD-A962-48F1A43BB29C",
  "exportOptions": {
    "_class": "exportOptions",
    "do_objectID": "8ABA2858-C295-474D-9615-33444EEABF73",
    "exportFormats": [
      {
        "_class": "exportFormat",
        "absoluteSize": 0,
        "fileFormat": "svg",
        "name": "",
        "namingScheme": 0,
        "scale": 1,
        "visibleScaleType": 0
      }
    ],
    "includedLayerIds": [
    ],
    "layerOptions": 0,
    "shouldTrim": false
  },
  "frame": {
    "_class": "rect",
    "constrainProportions": false,
    "do_objectID": "12AD0B38-FDB2-43CD-B38C-54E93836836B",
    "height": 144,
    "width": 144,
    "x": -2950,
    "y": -1198
  },
  "hasBackgroundColor": false,
  "hasClickThrough": true,
  "hasClippingMask": false,
  "horizontalRulerData": {
    "_class": "rulerData",
    "base": 0,
    "do_objectID": "4F5BDEA2-8B37-4BCD-A456-3A3C5DF65775",
    "guides": [
    ]
  },
  "includeBackgroundColorInExport": true,
  "includeBackgroundColorInInstance": false,
  "includeInCloudUpload": true,
  "isFixedToViewport": false,
  "isFlippedHorizontal": false,
  "isFlippedVertical": false,
  "isFlowHome": false,
  "isLocked": false,
  "isVisible": true,
  "layerListExpandedType": 2,
  "layers": [
    {
      "class": "shapeGroup",
      "id": "7F621DE4-ED35-42BD-9273-C7294C2C6139"
    }
  ],
  "name": "Icons/Line/Circle uno",
  "nameIsFixed": true,
  "resizesContent": false,
  "resizingConstraint": 63,
  "resizingType": 0,
  "rotation": 0,
  "shouldBreakMaskChain": true,
  "style": {
    "_class": "style",
    "do_objectID": "3F586664-A160-4CE4-AD2F-8E6335CB96B4",
    "endMarkerType": 0,
    "miterLimit": 10,
    "startMarkerType": 0,
    "windingRule": 1
  },
  "symbolID": "B0336747-E1EF-45FA-91FA-B57580822971",
  "verticalRulerData": {
    "_class": "rulerData",
    "base": 0,
    "do_objectID": "18B08EA7-D1CF-4EFE-AE08-8AD5BABFBE9D",
    "guides": [
    ]
  }
}