{
  "_class": "symbolInstance",
  "booleanOperation": -1,
  "clippingMaskMode": 0,
  "do_objectID": "D7CB9042-8CB1-4A5F-A9EA-86DA711AA5E8",
  "exportOptions": {
    "_class": "exportOptions",
    "do_objectID": "6C384002-FC59-4CBD-8F0A-A764E3EFBE27",
    "exportFormats": [
    ],
    "includedLayerIds": [
    ],
    "layerOptions": 0,
    "shouldTrim": false
  },
  "frame": {
    "_class": "rect",
    "constrainProportions": true,
    "do_objectID": "94CDBAED-ED20-4688-B66E-96A36678CA43",
    "height": 64,
    "width": 64,
    "x": 47,
    "y": 0
  },
  "hasClippingMask": false,
  "horizontalSpacing": 0,
  "isFixedToViewport": false,
  "isFlippedHorizontal": false,
  "isFlippedVertical": false,
  "isLocked": false,
  "isVisible": true,
  "layerListExpandedType": 0,
  "name": "Icons/Line/Economy Copy 2",
  "nameIsFixed": false,
  "overrideValues": [
    {
      "_class": "overrideValue",
      "overrideName": "28384F69-A9DA-49DC-AEEF-641F71B0A092_layerStyle",
      "value": "93D3E64F-F087-453B-8400-DE1DC0FA6861"
    }
  ],
  "resizingConstraint": 63,
  "resizingType": 0,
  "rotation": 0,
  "scale": 1,
  "shouldBreakMaskChain": false,
  "style": {
    "_class": "style",
    "do_objectID": "20F1AF2B-D71D-475C-AEF3-DE13ECC8FB07",
    "endMarkerType": 0,
    "miterLimit": 10,
    "startMarkerType": 0,
    "windingRule": 1
  },
  "symbolID": "3F233C1E-8A2B-4BB5-AA5E-2758D8313F34",
  "verticalSpacing": 0
}