{
  "_class": "shapePath",
  "booleanOperation": -1,
  "clippingMaskMode": 0,
  "do_objectID": "1F81ECD4-C03F-4732-8D34-D46AFF3750A1",
  "edited": true,
  "exportOptions": {
    "_class": "exportOptions",
    "do_objectID": "3334F480-F0D2-4B34-92B7-174E50399A52",
    "exportFormats": [
    ],
    "includedLayerIds": [
    ],
    "layerOptions": 0,
    "shouldTrim": false
  },
  "frame": {
    "_class": "rect",
    "constrainProportions": false,
    "do_objectID": "CDA503C4-6A98-48DB-B3C5-97F1616A57F3",
    "height": 20.3679859091686,
    "width": 70.5937003783212,
    "x": 32.84114226785601,
    "y": 32.78035949051841
  },
  "hasClippingMask": false,
  "isClosed": true,
  "isFixedToViewport": false,
  "isFlippedHorizontal": false,
  "isFlippedVertical": false,
  "isLocked": false,
  "isVisible": true,
  "layerListExpandedType": 0,
  "name": "Path",
  "nameIsFixed": false,
  "pointRadiusBehaviour": 1,
  "points": [
    {
      "_class": "curvePoint",
      "cornerRadius": 0,
      "curveFrom": "{0.24191387847865012, 0.6282552083333337}",
      "curveMode": 4,
      "curveTo": "{0.17120452732499511, 0}",
      "hasCurveFrom": true,
      "hasCurveTo": false,
      "point": "{0.17120452732499511, 0}"
    },
    {
      "_class": "curvePoint",
      "cornerRadius": 0,
      "curveFrom": "{0.72001474992850789, 0.57052083333333403}",
      "curveMode": 3,
      "curveTo": "{0.44641110157884434, 0.93921875000000066}",
      "hasCurveFrom": true,
      "hasCurveTo": true,
      "point": "{0.62795939254376065, 0.6945703124999999}"
    },
    {
      "_class": "curvePoint",
      "cornerRadius": 0,
      "curveFrom": "{0.82866377688475479, 0}",
      "curveMode": 4,
      "curveTo": "{0.79281242004184171, 0.31854166666666683}",
      "hasCurveFrom": false,
      "hasCurveTo": true,
      "point": "{0.82866377688475479, 0}"
    },
    {
      "_class": "curvePoint",
      "cornerRadius": 0,
      "curveFrom": "{0.89493686127541716, 0}",
      "curveMode": 1,
      "curveTo": "{0.89493686127541716, 0}",
      "hasCurveFrom": false,
      "hasCurveTo": false,
      "point": "{0.89493686127541716, 0}"
    },
    {
      "_class": "curvePoint",
      "cornerRadius": 0,
      "curveFrom": "{1, 1}",
      "curveMode": 1,
      "curveTo": "{1, 1}",
      "hasCurveFrom": false,
      "hasCurveTo": false,
      "point": "{1, 1}"
    },
    {
      "_class": "curvePoint",
      "cornerRadius": 0,
      "curveFrom": "{0, 1}",
      "curveMode": 1,
      "curveTo": "{0, 1}",
      "hasCurveFrom": false,
      "hasCurveTo": false,
      "point": "{0, 1}"
    },
    {
      "_class": "curvePoint",
      "cornerRadius": 0,
      "curveFrom": "{0.10505937598771839, 0}",
      "curveMode": 1,
      "curveTo": "{0.10505937598771839, 0}",
      "hasCurveFrom": false,
      "hasCurveTo": false,
      "point": "{0.10505937598771839, 0}"
    }
  ],
  "resizingConstraint": 63,
  "resizingType": 0,
  "rotation": 0,
  "shouldBreakMaskChain": false,
  "style": {
    "_class": "style",
    "do_objectID": "97169230-3ACB-42B4-BB0C-6176D2F85C54",
    "endMarkerType": 0,
    "miterLimit": 10,
    "startMarkerType": 0,
    "windingRule": 1
  }
}