{
  "_class": "symbolMaster",
  "backgroundColor": {
    "_class": "color",
    "alpha": 1,
    "blue": 1,
    "do_objectID": "544A0152-240C-41DC-9CA5-50DBAA4045A4",
    "green": 1,
    "red": 1
  },
  "booleanOperation": -1,
  "changeIdentifier": 13423,
  "clippingMaskMode": 0,
  "do_objectID": "7FF065C0-D5D9-40AF-B5F9-148DDA5D0D37",
  "exportOptions": {
    "_class": "exportOptions",
    "do_objectID": "B25DD20F-9AB0-409C-8259-A508F595E9C8",
    "exportFormats": [
      {
        "_class": "exportFormat",
        "absoluteSize": 0,
        "fileFormat": "svg",
        "name": "",
        "namingScheme": 0,
        "scale": 1,
        "visibleScaleType": 0
      }
    ],
    "includedLayerIds": [
    ],
    "layerOptions": 0,
    "shouldTrim": false
  },
  "frame": {
    "_class": "rect",
    "constrainProportions": false,
    "do_objectID": "EC33B9C3-457C-4235-85D1-4C3C0353BBAC",
    "height": 144,
    "width": 144,
    "x": -1398,
    "y": 22
  },
  "hasBackgroundColor": false,
  "hasClickThrough": true,
  "hasClippingMask": false,
  "horizontalRulerData": {
    "_class": "rulerData",
    "base": 0,
    "do_objectID": "AC1F3AD0-343A-4AA8-980B-3D501B0F0937",
    "guides": [
    ]
  },
  "includeBackgroundColorInExport": true,
  "includeBackgroundColorInInstance": false,
  "includeInCloudUpload": true,
  "isFixedToViewport": false,
  "isFlippedHorizontal": false,
  "isFlippedVertical": false,
  "isFlowHome": false,
  "isLocked": false,
  "isVisible": true,
  "layerListExpandedType": 2,
  "layers": [
    {
      "class": "shapeGroup",
      "id": "253FD80E-08F2-4F0C-8517-4E59BEA6CE71"
    }
  ],
  "name": "Icons/Line/Actions/Empty Search",
  "nameIsFixed": true,
  "resizesContent": false,
  "resizingConstraint": 63,
  "resizingType": 0,
  "rotation": 0,
  "shouldBreakMaskChain": true,
  "style": {
    "_class": "style",
    "do_objectID": "0D5B42EE-F3E8-465A-947B-552757F91558",
    "endMarkerType": 0,
    "miterLimit": 10,
    "startMarkerType": 0,
    "windingRule": 1
  },
  "symbolID": "2DED8D77-E900-46EB-B9A7-DD178F57055E",
  "verticalRulerData": {
    "_class": "rulerData",
    "base": 0,
    "do_objectID": "D6FE03D4-9F46-44EC-925C-4FC6E5C230D5",
    "guides": [
    ]
  }
}