{
  "_class": "shapePath",
  "booleanOperation": -1,
  "clippingMaskMode": 0,
  "do_objectID": "DEA79214-C191-4993-A39A-87D0B10F6EE8",
  "edited": true,
  "exportOptions": {
    "_class": "exportOptions",
    "do_objectID": "CDCB37E0-7AED-4FAE-A4E8-881357E12A55",
    "exportFormats": [
    ],
    "includedLayerIds": [
    ],
    "layerOptions": 0,
    "shouldTrim": false
  },
  "frame": {
    "_class": "rect",
    "constrainProportions": false,
    "do_objectID": "E37BD1CD-CC32-48C4-98E0-C42EB7EB3E9B",
    "height": 2.04411764705884,
    "width": 2.043879907621246,
    "x": 67.03926096997692,
    "y": 45.78823529411762
  },
  "hasClippingMask": false,
  "isClosed": true,
  "isFixedToViewport": false,
  "isFlippedHorizontal": false,
  "isFlippedVertical": false,
  "isLocked": false,
  "isVisible": true,
  "layerListExpandedType": 0,
  "name": "Fill 423",
  "nameIsFixed": false,
  "pointRadiusBehaviour": 1,
  "points": [
    {
      "_class": "curvePoint",
      "cornerRadius": 0,
      "curveFrom": "{0.3125, 0.83149999999999835}",
      "curveMode": 1,
      "curveTo": "{0.3125, 0.83149999999999835}",
      "hasCurveFrom": false,
      "hasCurveTo": false,
      "point": "{0.3125, 0.83149999999999835}"
    },
    {
      "_class": "curvePoint",
      "cornerRadius": 0,
      "curveFrom": "{0.6875, 0.83149999999999835}",
      "curveMode": 1,
      "curveTo": "{0.6875, 0.83149999999999835}",
      "hasCurveFrom": false,
      "hasCurveTo": false,
      "point": "{0.6875, 0.83149999999999835}"
    },
    {
      "_class": "curvePoint",
      "cornerRadius": 0,
      "curveFrom": "{0.6875, 0.16850000000000165}",
      "curveMode": 1,
      "curveTo": "{0.6875, 0.16850000000000165}",
      "hasCurveFrom": false,
      "hasCurveTo": false,
      "point": "{0.6875, 0.16850000000000165}"
    },
    {
      "_class": "curvePoint",
      "cornerRadius": 0,
      "curveFrom": "{0.3125, 0.16850000000000165}",
      "curveMode": 1,
      "curveTo": "{0.3125, 0.16850000000000165}",
      "hasCurveFrom": false,
      "hasCurveTo": false,
      "point": "{0.3125, 0.16850000000000165}"
    }
  ],
  "resizingConstraint": 63,
  "resizingType": 0,
  "rotation": 0,
  "shouldBreakMaskChain": false,
  "style": {
    "_class": "style",
    "do_objectID": "3F5BD876-2DFE-43B1-A088-D268CE04C245",
    "endMarkerType": 0,
    "fills": [
      {
        "_class": "fill",
        "color": {
          "_class": "color",
          "alpha": 1,
          "blue": 0.051,
          "green": 0.07100000000000001,
          "red": 0.118
        },
        "fillType": 0,
        "isEnabled": true,
        "noiseIndex": 0,
        "noiseIntensity": 0,
        "patternFillType": 1,
        "patternTileScale": 1
      }
    ],
    "miterLimit": 10,
    "startMarkerType": 0,
    "windingRule": 1
  }
}